{
	"allowedScopes": [
		"environment"
	],
	"description": "This setting is necessary, if you want to use automations and functions to execute http request to resources in private networks. If you assign an EdgeConnect to a certain hostname, calls to the 'fetch'-function in the dynatrace runtime to that hostname will be intercepted and executed from the EdgeConnect. The javascript code will behave as if the call was executed directly by the runtime.",
	"displayName": "Http Requests for EdgeConnect",
	"documentation": "",
	"dynatrace": "1",
	"enums": {},
	"maxObjects": 1,
	"multiObject": false,
	"properties": {
		"externalUrls": {
			"description": "",
			"displayName": "",
			"documentation": "",
			"maxObjects": 1,
			"modificationPolicy": "DEFAULT",
			"nullable": false,
			"type": {
				"$ref": "#/types/HostLocationMappings"
			}
		}
	},
	"schemaGroups": [
		"group:dt-javascript-runtime",
		"group:preferences"
	],
	"schemaId": "builtin:dt-javascript-runtime.edge-http-targets",
	"types": {
		"HostLocationMapping": {
			"description": "",
			"displayName": "HostEdgeConnectMapping",
			"documentation": "",
			"properties": {
				"host": {
					"constraints": [
						{
							"maxLength": 256,
							"minLength": 1,
							"type": "LENGTH"
						},
						{
							"customValidatorId": "hostname-validator",
							"type": "CUSTOM_VALIDATOR_REF"
						}
					],
					"default": "*.example.com",
					"description": "",
					"displayName": "Host",
					"documentation": "Either an IP, or a domain name which may contain a wildcard ('\\*') as the leftmost label. If a '\\*' is used, it must be followed by at least two labels.",
					"maxObjects": 1,
					"modificationPolicy": "DEFAULT",
					"nullable": false,
					"type": "text"
				},
				"location": {
					"constraints": [
						{
							"maxLength": 32,
							"minLength": 1,
							"type": "LENGTH"
						},
						{
							"customValidatorId": "location-validator",
							"type": "CUSTOM_VALIDATOR_REF"
						}
					],
					"default": "",
					"description": "",
					"displayName": "EdgeConnect name",
					"documentation": "",
					"maxObjects": 1,
					"modificationPolicy": "DEFAULT",
					"nullable": false,
					"type": "text"
				}
			},
			"summaryPattern": "Map host {host} to EdgeConnect {location}.",
			"type": "object",
			"version": "0",
			"versionInfo": ""
		},
		"HostLocationMappings": {
			"description": "Specifies allowed hosts and if the allow list should be enforced.",
			"displayName": "HostEdgeConnectMappings",
			"documentation": "",
			"properties": {
				"mappings": {
					"description": "",
					"displayName": "Host to EdgeConnect Mappings",
					"documentation": "Calls to the specified hosts will be executed by the specified EdgeConnect.",
					"items": {
						"description": "Calls to the specified hosts will be executed by the specified EdgeConnect.",
						"displayName": "Host to EdgeConnect Mappings",
						"documentation": "",
						"type": {
							"$ref": "#/types/HostLocationMapping"
						}
					},
					"maxObjects": 50,
					"minObjects": 0,
					"modificationPolicy": "DEFAULT",
					"nullable": false,
					"type": "set"
				}
			},
			"summaryPattern": "",
			"type": "object",
			"version": "0",
			"versionInfo": ""
		}
	},
	"version": "0.0.3"
}